{
  "display_name": "Elite: Dangerous",
  "thumbnail": {
    "remote": false,
    "file": "Screenshot_0001.bmp"
  },
  "tags": [ "EliteDangerous" ],
  "images": [
    {
      "remote": true,
      "file": "https://steamuserimages-a.akamaihd.net/ugc/616222083862756981/79F0361D34E0946296F268376D111F48B634894E/",
      "description": "Member: <a href='/members/TehGM'>TehGM</a>"
    },
    {
      "remote": true,
      "file": "https://steamuserimages-a.akamaihd.net/ugc/616222083862756749/B914637735A159E24FB8F355D3EED5E01301F31B/",
      "description": "Member: <a href='/members/TehGM'>TehGM</a>"
    },
    {
      "remote": true,
      "file": "https://steamuserimages-a.akamaihd.net/ugc/27367908918276715/9468F8AE96E1569D983A13146F7131F62653B035/",
      "description": "Member: <a href='/members/TehGM'>TehGM</a>"
    },
    {
      "remote": true,
      "file": "https://steamuserimages-a.akamaihd.net/ugc/633104874576585522/FE79EF959CEAE96665B84E0EB03EEAA51498BA78/",
      "description": "Member: <a href='/members/TehGM'>TehGM</a>"
    },
    {
      "remote": true,
      "file": "https://steamuserimages-a.akamaihd.net/ugc/633104874576585106/C8E04B15A0CFA90587AA0E271D2A43196C16A35F/",
      "description": "Member: <a href='/members/TehGM'>TehGM</a>"
    },
    {
      "remote": true,
      "file": "https://steamuserimages-a.akamaihd.net/ugc/633104874576584877/9AB7BCF7DEC8492BC2A6E24DF2DDA3CE727A320D/",
      "description": "Member: <a href='/members/TehGM'>TehGM</a>"
    },
    {
      "remote": true,
      "file": "https://steamuserimages-a.akamaihd.net/ugc/633104874576579797/A4727B1AEDDF0E46F6BBE68B0FBD0DFB8C82099A/",
      "description": "Member: <a href='/members/TehGM'>TehGM</a>"
    },
    {
      "remote": true,
      "file": "https://steamuserimages-a.akamaihd.net/ugc/633104874576578997/B31156E422610B94DC5218513FE5065538A5D5FF/",
      "description": "Member: <a href='/members/TehGM'>TehGM</a>"
    },
    {
      "remote": true,
      "file": "https://steamuserimages-a.akamaihd.net/ugc/633104874576578128/14534D54C4D1B1ED2DA8DE1B84728DB0114D2467/",
      "description": "Member: <a href='/members/TehGM'>TehGM</a>"
    },
    {
      "remote": true,
      "file": "https://steamuserimages-a.akamaihd.net/ugc/633104874576578461/929CBF05DD493FDB4CF28EE23E27DF32A5D694A6/",
      "description": "Member: <a href='/members/TehGM'>TehGM</a>"
    },
    {
      "remote": true,
      "file": "https://steamuserimages-a.akamaihd.net/ugc/633104874576575656/D566461FB3C45E0BF0C996EF9C3AD5A02E220B65/",
      "description": "Member: <a href='/members/TehGM'>TehGM</a>"
    },
    {
      "remote": false,
      "file": "Screenshot_0001.bmp",
      "title": "Watching the Star",
      "description": "Location: Wredguia ZX-U d2-26 B 1<br/>Member: <a href='/members/TehGM'>TehGM</a>"
    },
    {
      "remote": false,
      "file": "Screenshot_0001.png",
      "title": "Watching the Star",
      "description": "Location: Wredguia ZX-U d2-26 B 1<br/>Member: <a href='/members/TehGM'>TehGM</a>"
    },
    {
      "remote": false,
      "file": "Wredguia ZX-U d2-26-Wredguia ZX-U d2-26 B 1 (14.07.2019 08-24-38).png",
      "title": "Watching the Star",
      "description": "Location: Wredguia ZX-U d2-26 B 1<br/>Member: <a href='/members/TehGM'>TehGM</a>"
    },
    {
      "remote": false,
      "file": "Wredguia ZX-U d2-26-Wredguia ZX-U d2-26 B 1 (14.07.2019 08-35-36).png",
      "title": "Watching the Star",
      "description": "Location: Wredguia ZX-U d2-26 B 1<br/>Member: <a href='/members/TehGM'>TehGM</a>"
    },
    {
      "remote": false,
      "file": "HighResScreenShot_2019-06-19_15-23-48.png",
      "description": "Member: <a href='/members/TehGM'>TehGM</a>"
    },
    {
      "remote": false,
      "file": "HighResScreenShot_2019-06-23_20-47-24.png",
      "description": "Member: <a href='/members/TehGM'>TehGM</a>"
    },
    {
      "remote": false,
      "file": "HighResScreenShot_2019-06-23_20-48-52.png",
      "description": "Member: <a href='/members/TehGM'>TehGM</a>"
    },
    {
      "remote": false,
      "file": "HighResScreenShot_2019-06-23_20-50-04.png",
      "description": "Member: <a href='/members/TehGM'>TehGM</a>"
    },
    {
      "remote": false,
      "file": "HighResScreenShot_2019-06-23_22-28-38.png",
      "description": "Member: <a href='/members/TehGM'>TehGM</a>"
    },
    {
      "remote": false,
      "file": "HighResScreenShot_2019-06-24_21-04-40.png",
      "description": "Member: <a href='/members/TehGM'>TehGM</a>"
    },
    {
      "remote": false,
      "file": "HighResScreenShot_2019-06-25_15-47-33.png",
      "description": "Member: <a href='/members/TehGM'>TehGM</a>"
    },
    {
      "remote": false,
      "file": "HighResScreenShot_2019-07-11_12-40-50.png",
      "description": "Member: <a href='/members/TehGM'>TehGM</a>"
    },
    {
      "remote": false,
      "file": "HighResScreenShot_2019-07-11_14-54-54.png",
      "title": "Twin Pulsars",
      "description": "Member: <a href='/members/TehGM'>TehGM</a>"
    },
    {
      "remote": false,
      "file": "HighResScreenShot_2019-07-11_14-56-18.png",
      "title": "Twin Pulsars",
      "description": "Member: <a href='/members/TehGM'>TehGM</a>"
    },
    {
      "remote": false,
      "file": "HighResScreenShot_2019-07-11_14-57-11.png",
      "title": "Twin Pulsars",
      "description": "Member: <a href='/members/TehGM'>TehGM</a>"
    },
    {
      "remote": false,
      "file": "HighResScreenShot_2019-07-11_14-59-00.png",
      "title": "Twin Pulsars",
      "description": "Member: <a href='/members/TehGM'>TehGM</a>"
    },
    {
      "remote": false,
      "file": "HighResScreenShot_2019-07-13_13-24-02.png",
      "title": "Gas Giant moon's canyon",
      "description": "Member: <a href='/members/TehGM'>TehGM</a>"
    },
    {
      "remote": false,
      "file": "HighResScreenShot_2019-07-13_13-24-26.png",
      "title": "Gas Giant moon's canyon",
      "description": "Member: <a href='/members/TehGM'>TehGM</a>"
    },
    {
      "remote": false,
      "file": "Screenshot_0003.bmp",
      "title": "Gas Giant moon's canyon",
      "description": "Member: <a href='/members/TehGM'>TehGM</a>"
    },
    {
      "remote": false,
      "file": "Screenshot_0002.bmp",
      "description": "Member: <a href='/members/TehGM'>TehGM</a>"
    }
  ]
}